[
	{
		"key": "krefeld",
		"title": "KInvFöG-Maßnahmen",
		"data": "data-krefeld",
		"config": "config-krefeld",
		"lat": 51.340164,
		"lng": 6.602664,
		"zoom": 12
	},
	{
		"key": "trees2015",
		"title": "Neue Bäume in 2015",
		"data": "data-trees-2015",
		"config": "config-trees",
		"lat": 51.340164,
		"lng": 6.602664,
		"zoom": 12
	},
	{
		"key": "trees2016",
		"title": "Neue Bäume in 2016",
		"data": "data-trees-2016",
		"config": "config-trees",
		"lat": 51.340164,
		"lng": 6.602664,
		"zoom": 12
	},
	{
		"key": "trees2017",
		"title": "Neue Bäume in 2017",
		"data": "data-trees-2017",
		"config": "config-trees",
		"lat": 51.340164,
		"lng": 6.602664,
		"zoom": 12
	}
]