[
	{
		"title": "Bäume",
		"menu": [
			{
				"title": "2015",
				"id": "trees-2015",
				"data": "data-trees-2015",
				"config": "config-trees",
				"type": "point",
				"icon": "fa-leaf",
				"color": "#3cc2ff"
			},
			{
				"title": "2016",
				"id": "trees-2016",
				"data": "data-trees-2016",
				"config": "config-trees",
				"type": "point",
				"icon": "fa-leaf",
				"color": "#3cc2ff"
			},
			{
				"title": "2017",
				"id": "trees-2017",
				"data": "data-trees-2017",
				"config": "config-trees",
				"type": "point",
				"icon": "fa-leaf",
				"color": "#3cc2ff"
			}
		]
	},
	{
		"title": "Radwege",
		"menu": [
			{
				"title": "alle",
				"id": "kinvfog-bikeways",
				"data": "data-kinvfog-bikeways",
				"config": "config-kinvfog-bikeways",
				"_type": "polygon",
				"type": "point",
				"icon": "fa-bicycle",
				"color": "#3cc2ff"
			}
		]
	},
	{
		"title": "Straßen",
		"menu": [
			{
				"title": "alle",
				"id": "kinvfog-streets",
				"data": "data-kinvfog-streets",
				"config": "config-kinvfog-streets",
				"_type": "polygon",
				"type": "point",
				"icon": "fa-car",
				"color": "#3cc2ff"
			}
		]
	},
	{
		"title": "Bauen",
		"menu": [
			{
				"title": "Gebäude",
				"id": "kinvfog-buildings",
				"data": "data-kinvfog",
				"config": "config-kinvfog",
				"type": "point",
				"icon": "shield",
				"color": "#3cc2ff"
			},
			{
				"title": "Neubau von Schulen",
				"id": "school-new",
				"data": "data-schule-neubau",
				"config": "config-schule-neubau",
				"type": "point",
				"icon": "shield",
				"color": "#3cc2ff"
			},
			{
				"title": "Schulsanierungen",
				"id": "school-repair",
				"data": "data-schule-bestand",
				"config": "config-schule-bestand",
				"type": "point",
				"icon": "shield",
				"color": "#3cc2ff"
			}
		]
	}
]